{"directed": true, "multigraph": false, "graph": {}, "nodes": [{"lat": 39.3630371094, "lon": -0.4648583233, "name": "Picassent", "original_ids": [45], "id": 0}, {"lat": 39.3848648071, "lon": -0.4672611058, "name": "Sant Ramon", "original_ids": [46], "id": 1}, {"lat": 39.3939056396, "lon": -0.4640137851, "name": "Real\u00f3n", "original_ids": [47], "id": 2}, {"lat": 39.4231338501, "lon": -0.4606527686, "name": "Col\u00b7legi El Vedat", "original_ids": [48], "id": 3}, {"lat": 39.4346466064, "lon": -0.4609861076, "name": "Torrent", "original_ids": [32], "id": 4}, {"lat": 39.4331207275, "lon": -0.4371583462, "name": "Picanya", "original_ids": [31], "id": 5}, {"lat": 39.4322624207, "lon": -0.4180611074, "name": "Paiporta", "original_ids": [30], "id": 6}, {"lat": 39.4408111572, "lon": -0.4106472135, "name": "Val\u00e8ncia Sud", "original_ids": [29], "id": 7}, {"lat": 39.4510345459, "lon": -0.4028027654, "name": "Sant Isidre", "original_ids": [28], "id": 8}, {"lat": 39.4545707703, "lon": -0.3983833194, "name": "Safranar", "original_ids": [27], "id": 9}, {"lat": 39.456451416, "lon": -0.3905083239, "name": "Patraix", "original_ids": [26], "id": 10}, {"lat": 39.4592018127, "lon": -0.3845416605, "name": "Jes\u00fas", "original_ids": [25], "id": 11}, {"lat": 39.4662017822, "lon": -0.3816333413, "name": "Pl. Espanya", "original_ids": [49], "id": 12}, {"lat": 39.4703025818, "lon": -0.3850361109, "name": "\u00c0ngel Guimer\u00e0", "original_ids": [17], "id": 13}, {"lat": 39.4788665771, "lon": -0.3912055492, "name": "T\u00faria", "original_ids": [50], "id": 14}, {"lat": 39.4846305847, "lon": -0.3950361013, "name": "Campanar", "original_ids": [51], "id": 15}, {"lat": 39.4910316467, "lon": -0.3993369341, "name": "Beniferri", "original_ids": [52], "id": 16}, {"lat": 39.4995765686, "lon": -0.4021083415, "name": "Empalme", "original_ids": [53], "id": 17}, {"lat": 39.5084152222, "lon": -0.4067361057, "name": "Burjassot", "original_ids": [70], "id": 18}, {"lat": 39.5135307312, "lon": -0.4119972289, "name": "Burjassot - Godella", "original_ids": [71], "id": 19}, {"lat": 39.5195045471, "lon": -0.4144555628, "name": "Godella", "original_ids": [72], "id": 20}, {"lat": 39.5287094116, "lon": -0.4075777829, "name": "Rocafort", "original_ids": [73], "id": 21}, {"lat": 39.5366096497, "lon": -0.4028777778, "name": "Massarrojos", "original_ids": [74], "id": 22}, {"lat": 39.5435295105, "lon": -0.388461113, "name": "Moncada - Alfara", "original_ids": [75], "id": 23}, {"lat": 39.549987793, "lon": -0.3897444308, "name": "Seminari - CEU", "original_ids": [76], "id": 24}, {"lat": 39.5665817261, "lon": -0.4053777754, "name": "Masies", "original_ids": [77], "id": 25}, {"lat": 39.5819320679, "lon": -0.4431444407, "name": "Horta Vella", "original_ids": [78], "id": 26}, {"lat": 39.5906066895, "lon": -0.4575305581, "name": "B\u00e9tera", "original_ids": [104], "id": 27}, {"lat": 39.0840072632, "lon": -0.5160138607, "name": "Villanueva de Castell\u00f3n", "original_ids": [34], "id": 28}, {"lat": 39.1170501709, "lon": -0.5235260129, "name": "Alberic", "original_ids": [35], "id": 29}, {"lat": 39.1438064575, "lon": -0.5187610984, "name": "Massalav\u00e9s", "original_ids": [36], "id": 30}, {"lat": 39.1737976074, "lon": -0.5158861279, "name": "Montortal", "original_ids": [37], "id": 31}, {"lat": 39.193813324, "lon": -0.5102638602, "name": "L'Alc\u00fadia", "original_ids": [38], "id": 32}, {"lat": 39.216293335, "lon": -0.5196194649, "name": "Benimodo", "original_ids": [39], "id": 33}, {"lat": 39.2267990112, "lon": -0.5249416828, "name": "Carlet", "original_ids": [40], "id": 34}, {"lat": 39.2495574951, "lon": -0.4919772148, "name": "Ausi\u00e0s March", "original_ids": [41], "id": 35}, {"lat": 39.2629394531, "lon": -0.4748860002, "name": "Alginet", "original_ids": [127], "id": 36}, {"lat": 39.2894058228, "lon": -0.4640861154, "name": "Font Almaguer", "original_ids": [42], "id": 37}, {"lat": 39.3218841553, "lon": -0.4667472243, "name": "Espioca", "original_ids": [43], "id": 38}, {"lat": 39.3532447815, "lon": -0.4736869931, "name": "Omet", "original_ids": [44], "id": 39}, {"lat": 39.4318122864, "lon": -0.4728333354, "name": "Torrent Avinguda", "original_ids": [33], "id": 40}, {"lat": 39.5023803711, "lon": -0.4120722115, "name": "Canterer\u00eda", "original_ids": [54], "id": 41}, {"lat": 39.5018768311, "lon": -0.4194111228, "name": "Benim\u00e0met", "original_ids": [55], "id": 42}, {"lat": 39.4987373352, "lon": -0.4254194498, "name": "Les Carolines/Fira", "original_ids": [56], "id": 43}, {"lat": 39.4958457947, "lon": -0.435323, "name": "Campament", "original_ids": [57], "id": 44}, {"lat": 39.4988098145, "lon": -0.4419719875, "name": "Paterna", "original_ids": [58], "id": 45}, {"lat": 39.505657196, "lon": -0.4551055431, "name": "Santa Rita", "original_ids": [59], "id": 46}, {"lat": 39.5111732483, "lon": -0.4645166695, "name": "Fuente del Jarro", "original_ids": [60], "id": 47}, {"lat": 39.5268058777, "lon": -0.4871222079, "name": "La Canyada", "original_ids": [61], "id": 48}, {"lat": 39.5378417969, "lon": -0.4979777634, "name": "La Vallesa", "original_ids": [62], "id": 49}, {"lat": 39.5433349609, "lon": -0.5139539838, "name": "Entrepins", "original_ids": [63], "id": 50}, {"lat": 39.5498657227, "lon": -0.5279861093, "name": "El Clot", "original_ids": [105], "id": 51}, {"lat": 39.5555725098, "lon": -0.5316972136, "name": "Montesol", "original_ids": [64], "id": 52}, {"lat": 39.561832428, "lon": -0.5359194279, "name": "L'Eliana", "original_ids": [65], "id": 53}, {"lat": 39.5686645508, "lon": -0.5419166684, "name": "Torre del Virrei", "original_ids": [130], "id": 54}, {"lat": 39.5827636719, "lon": -0.5622777939, "name": "La Pobla de Vallbona", "original_ids": [66], "id": 55}, {"lat": 39.5927238464, "lon": -0.5780805349, "name": "Benaguasil 1r", "original_ids": [67], "id": 56}, {"lat": 39.5988807678, "lon": -0.5839277506, "name": "Benaguasil 2n", "original_ids": [68], "id": 57}, {"lat": 39.6228408813, "lon": -0.590277791, "name": "Ll\u00edria", "original_ids": [69], "id": 58}, {"lat": 39.5433349609, "lon": -0.5594444275, "name": "Riba-roja de T\u00faria", "original_ids": [131], "id": 59}, {"lat": 39.5380554199, "lon": -0.5466666818, "name": "Masia de Traver", "original_ids": [132], "id": 60}, {"lat": 39.5304832458, "lon": -0.5342069864, "name": "Val\u00e8ncia la Vella", "original_ids": [135], "id": 61}, {"lat": 39.5172233582, "lon": -0.5158333182, "name": "La Presa", "original_ids": [134], "id": 62}, {"lat": 39.4988899231, "lon": -0.4844444394, "name": "La Cova", "original_ids": [133], "id": 63}, {"lat": 39.4926490784, "lon": -0.4672361016, "name": "Rosas", "original_ids": [116], "id": 64}, {"lat": 39.4895896912, "lon": -0.4590654373, "name": "Manises", "original_ids": [115], "id": 65}, {"lat": 39.4848327637, "lon": -0.4505681992, "name": "Salt de l'Aigua", "original_ids": [114], "id": 66}, {"lat": 39.481086731, "lon": -0.441880554, "name": "Quart de Poblet", "original_ids": [113], "id": 67}, {"lat": 39.4776191711, "lon": -0.4331833422, "name": "Faitanar", "original_ids": [22], "id": 68}, {"lat": 39.4760093689, "lon": -0.4243694544, "name": "Mislata - Almassil", "original_ids": [21], "id": 69}, {"lat": 39.4738235474, "lon": -0.418305546, "name": "Mislata", "original_ids": [20], "id": 70}, {"lat": 39.4706573486, "lon": -0.4076305628, "name": "Nou d'Octubre", "original_ids": [19], "id": 71}, {"lat": 39.4682197571, "lon": -0.397574991, "name": "Av. del Cid", "original_ids": [18], "id": 72}, {"lat": 39.4671859741, "lon": -0.3773750067, "name": "X\u00e0tiva", "original_ids": [16], "id": 73}, {"lat": 39.4701461792, "lon": -0.3709277809, "name": "Col\u00f3n", "original_ids": [15], "id": 74}, {"lat": 39.4731559753, "lon": -0.3653166592, "name": "Alameda", "original_ids": [14], "id": 75}, {"lat": 39.4780044556, "lon": -0.361905545, "name": "Facultats-Manuel Broseta", "original_ids": [13], "id": 76}, {"lat": 39.4848518372, "lon": -0.3623333275, "name": "Benimaclet", "original_ids": [12], "id": 77}, {"lat": 39.4924316406, "lon": -0.3587944508, "name": "Machado", "original_ids": [11], "id": 78}, {"lat": 39.4956626892, "lon": -0.3552222252, "name": "Alboraya-Palmaret", "original_ids": [10], "id": 79}, {"lat": 39.5007629395, "lon": -0.352327764, "name": "Alboraya-Peris Arag\u00f3", "original_ids": [9], "id": 80}, {"lat": 39.4923667908, "lon": -0.4749194384, "name": "Aeroport", "original_ids": [117], "id": 81}, {"lat": 39.5122566223, "lon": -0.3542666733, "name": "Alm\u00e0ssera", "original_ids": [8], "id": 82}, {"lat": 39.5280303955, "lon": -0.3518194556, "name": "Meliana", "original_ids": [7], "id": 83}, {"lat": 39.5372238159, "lon": -0.3538694382, "name": "Foios", "original_ids": [6], "id": 84}, {"lat": 39.5452651978, "lon": -0.3482888937, "name": "Albalat dels Sorells", "original_ids": [5], "id": 85}, {"lat": 39.5615768433, "lon": -0.3408555686, "name": "Museros", "original_ids": [4], "id": 86}, {"lat": 39.5705604553, "lon": -0.3330333233, "name": "Massamagrell", "original_ids": [3], "id": 87}, {"lat": 39.5794181824, "lon": -0.3304361105, "name": "La Pobla de Farnals", "original_ids": [2], "id": 88}, {"lat": 39.5885238647, "lon": -0.3310583234, "name": "Rafelbunyol", "original_ids": [1], "id": 89}, {"lat": 39.4726257324, "lon": -0.3581166565, "name": "Arag\u00f3n", "original_ids": [24], "id": 90}, {"lat": 39.4703330994, "lon": -0.3503944576, "name": "Amistat-Casa de Salud", "original_ids": [23], "id": 91}, {"lat": 39.4664268494, "lon": -0.3429694474, "name": "Ayora", "original_ids": [128], "id": 92}, {"lat": 39.4649391174, "lon": -0.3382369876, "name": "Mar\u00edtim - Serrer\u00eda", "original_ids": [112], "id": 93}, {"lat": 39.4639778137, "lon": -0.3794222176, "name": "Bail\u00e9n", "original_ids": [106], "id": 94}], "links": [{"shape_id": {"2": 48}, "direction_id": {}, "headsign": {"L'Alc\u00fadia": 4, "Villanueva de Castell\u00f3n": 44}, "duration_avg": 110.0, "n_vehicles": 48, "d": 1328, "route_I_counts": {"2": 24, "40": 7, "45": 12, "46": 1, "50": 3, "54": 1}, "source": 0, "target": 39}, {"shape_id": {"48": 66}, "direction_id": {}, "headsign": {"B\u00e9tera": 26, "Empalme": 4, "Seminari - CEU": 34, "Val\u00e8ncia Sud": 2}, "duration_avg": 111.81818181818181, "n_vehicles": 66, "d": 2438, "route_I_counts": {"1": 33, "75": 1, "76": 14, "77": 6, "78": 1, "79": 1, "80": 3, "81": 1, "82": 6}, "source": 0, "target": 1}, {"shape_id": {"2": 70}, "direction_id": {}, "headsign": {"L'Alc\u00fadia": 4, "Picassent": 22, "Villanueva de Castell\u00f3n": 44}, "duration_avg": 204.85714285714286, "n_vehicles": 70, "d": 2438, "route_I_counts": {"2": 35, "40": 7, "41": 6, "45": 12, "46": 1, "47": 4, "50": 3, "54": 1, "55": 1}, "source": 1, "target": 0}, {"shape_id": {"48": 66}, "direction_id": {}, "headsign": {"B\u00e9tera": 26, "Empalme": 4, "Seminari - CEU": 34, "Val\u00e8ncia Sud": 2}, "duration_avg": 110.0, "n_vehicles": 66, "d": 1044, "route_I_counts": {"1": 33, "75": 1, "76": 14, "77": 6, "78": 1, "79": 1, "80": 3, "81": 1, "82": 6}, "source": 1, "target": 2}, {"shape_id": {"2": 70}, "direction_id": {}, "headsign": {"L'Alc\u00fadia": 4, "Picassent": 22, "Villanueva de Castell\u00f3n": 44}, "duration_avg": 110.0, "n_vehicles": 70, "d": 1044, "route_I_counts": {"2": 35, "40": 7, "41": 6, "45": 12, "46": 1, "47": 4, "50": 3, "54": 1, "55": 1}, "source": 2, "target": 1}, {"shape_id": {"48": 66}, "direction_id": {}, "headsign": {"B\u00e9tera": 26, "Empalme": 4, "Seminari - CEU": 34, "Val\u00e8ncia Sud": 2}, "duration_avg": 111.81818181818181, "n_vehicles": 66, "d": 3266, "route_I_counts": {"1": 33, "75": 1, "76": 14, "77": 6, "78": 1, "79": 1, "80": 3, "81": 1, "82": 6}, "source": 2, "target": 3}, {"shape_id": {"2": 70}, "direction_id": {}, "headsign": {"L'Alc\u00fadia": 4, "Picassent": 22, "Villanueva de Castell\u00f3n": 44}, "duration_avg": 110.85714285714286, "n_vehicles": 70, "d": 3266, "route_I_counts": {"2": 35, "40": 7, "41": 6, "45": 12, "46": 1, "47": 4, "50": 3, "54": 1, "55": 1}, "source": 3, "target": 2}, {"shape_id": {"48": 66}, "direction_id": {}, "headsign": {"B\u00e9tera": 26, "Empalme": 4, "Seminari - CEU": 34, "Val\u00e8ncia Sud": 2}, "duration_avg": 256.969696969697, "n_vehicles": 66, "d": 1281, "route_I_counts": {"1": 33, "75": 1, "76": 14, "77": 6, "78": 1, "79": 1, "80": 3, "81": 1, "82": 6}, "source": 3, "target": 4}, {"shape_id": {"2": 70}, "direction_id": {}, "headsign": {"L'Alc\u00fadia": 4, "Picassent": 22, "Villanueva de Castell\u00f3n": 44}, "duration_avg": 170.0, "n_vehicles": 70, "d": 1281, "route_I_counts": {"2": 35, "40": 7, "41": 6, "45": 12, "46": 1, "47": 4, "50": 3, "54": 1, "55": 1}, "source": 4, "target": 3}, {"shape_id": {"45": 126, "46": 4, "47": 14, "48": 132}, "direction_id": {}, "headsign": {"B\u00e9tera": 64, "Empalme": 6, "La Canyada": 2, "Ll\u00edria": 8, "Machado": 8, "Mar\u00edtim - Serrer\u00eda": 122, "Seminari - CEU": 62, "Val\u00e8ncia Sud": 4}, "duration_avg": 170.0, "n_vehicles": 276, "d": 2055, "route_I_counts": {"1": 66, "4": 7, "12": 61, "14": 4, "75": 1, "76": 14, "77": 6, "78": 1, "79": 1, "80": 3, "81": 1, "82": 6, "83": 14, "84": 19, "90": 1, "91": 1, "93": 5, "107": 61, "108": 4}, "source": 4, "target": 5}, {"shape_id": {"1": 13, "18": 2, "2": 3, "3": 2, "6": 126}, "direction_id": {}, "headsign": {"Torrent Avinguda": 146}, "duration_avg": 240.0, "n_vehicles": 146, "d": 1066, "route_I_counts": {"5": 8, "13": 63, "15": 2, "57": 3, "59": 4, "61": 1, "65": 2, "71": 63}, "source": 4, "target": 40}, {"shape_id": {"1": 13, "18": 2, "2": 141, "3": 2, "6": 126}, "direction_id": {}, "headsign": {"L'Alc\u00fadia": 4, "Picassent": 22, "Torrent": 68, "Torrent Avinguda": 146, "Villanueva de Castell\u00f3n": 44}, "duration_avg": 206.61971830985917, "n_vehicles": 284, "d": 2055, "route_I_counts": {"2": 69, "5": 8, "13": 63, "15": 2, "40": 7, "41": 6, "43": 20, "45": 12, "46": 1, "47": 4, "48": 14, "50": 3, "54": 1, "55": 1, "57": 3, "59": 4, "61": 1, "65": 2, "71": 63}, "source": 5, "target": 4}, {"shape_id": {"45": 126, "46": 4, "47": 14, "48": 132}, "direction_id": {}, "headsign": {"B\u00e9tera": 64, "Empalme": 6, "La Canyada": 2, "Ll\u00edria": 8, "Machado": 8, "Mar\u00edtim - Serrer\u00eda": 122, "Seminari - CEU": 62, "Val\u00e8ncia Sud": 4}, "duration_avg": 110.0, "n_vehicles": 276, "d": 1644, "route_I_counts": {"1": 66, "4": 7, "12": 61, "14": 4, "75": 1, "76": 14, "77": 6, "78": 1, "79": 1, "80": 3, "81": 1, "82": 6, "83": 14, "84": 19, "90": 1, "91": 1, "93": 5, "107": 61, "108": 4}, "source": 5, "target": 6}, {"shape_id": {"1": 13, "18": 2, "2": 141, "3": 2, "6": 126}, "direction_id": {}, "headsign": {"L'Alc\u00fadia": 4, "Picassent": 22, "Torrent": 68, "Torrent Avinguda": 146, "Villanueva de Castell\u00f3n": 44}, "duration_avg": 113.38028169014085, "n_vehicles": 284, "d": 1644, "route_I_counts": {"2": 69, "5": 8, "13": 63, "15": 2, "40": 7, "41": 6, "43": 20, "45": 12, "46": 1, "47": 4, "48": 14, "50": 3, "54": 1, "55": 1, "57": 3, "59": 4, "61": 1, "65": 2, "71": 63}, "source": 6, "target": 5}, {"shape_id": {"45": 126, "46": 4, "47": 14, "48": 132}, "direction_id": {}, "headsign": {"B\u00e9tera": 64, "Empalme": 6, "La Canyada": 2, "Ll\u00edria": 8, "Machado": 8, "Mar\u00edtim - Serrer\u00eda": 122, "Seminari - CEU": 62, "Val\u00e8ncia Sud": 4}, "duration_avg": 110.14492753623189, "n_vehicles": 276, "d": 1145, "route_I_counts": {"1": 66, "4": 7, "12": 61, "14": 4, "75": 1, "76": 14, "77": 6, "78": 1, "79": 1, "80": 3, "81": 1, "82": 6, "83": 14, "84": 19, "90": 1, "91": 1, "93": 5, "107": 61, "108": 4}, "source": 6, "target": 7}, {"shape_id": {"1": 13, "18": 2, "2": 141, "3": 2, "6": 126}, "direction_id": {}, "headsign": {"L'Alc\u00fadia": 4, "Picassent": 22, "Torrent": 68, "Torrent Avinguda": 146, "Villanueva de Castell\u00f3n": 44}, "duration_avg": 110.0, "n_vehicles": 284, "d": 1145, "route_I_counts": {"2": 69, "5": 8, "13": 63, "15": 2, "40": 7, "41": 6, "43": 20, "45": 12, "46": 1, "47": 4, "48": 14, "50": 3, "54": 1, "55": 1, "57": 3, "59": 4, "61": 1, "65": 2, "71": 63}, "source": 7, "target": 6}, {"shape_id": {"45": 126, "46": 4, "47": 140, "48": 146}, "direction_id": {}, "headsign": {"B\u00e9tera": 70, "Empalme": 12, "La Canyada": 8, "Ll\u00edria": 76, "Machado": 8, "Mar\u00edtim - Serrer\u00eda": 122, "Paterna": 54, "Seminari - CEU": 66}, "duration_avg": 114.15625, "n_vehicles": 416, "d": 1322, "route_I_counts": {"1": 73, "4": 70, "12": 61, "14": 4, "75": 1, "76": 14, "77": 6, "78": 1, "79": 1, "80": 3, "82": 6, "83": 14, "84": 19, "85": 2, "86": 3, "87": 3, "88": 5, "89": 3, "91": 1, "92": 23, "93": 38, "107": 61, "108": 4}, "source": 7, "target": 8}, {"shape_id": {"1": 137, "18": 2, "2": 139, "3": 2, "6": 126}, "direction_id": {}, "headsign": {"L'Alc\u00fadia": 2, "Picassent": 20, "Torrent": 68, "Torrent Avinguda": 140, "Val\u00e8ncia Sud": 132, "Villanueva de Castell\u00f3n": 44}, "duration_avg": 109.26108374384236, "n_vehicles": 406, "d": 1322, "route_I_counts": {"2": 69, "5": 68, "13": 63, "15": 2, "40": 7, "41": 6, "43": 20, "44": 1, "45": 12, "46": 1, "47": 4, "48": 14, "49": 1, "50": 3, "52": 1, "58": 22, "59": 13, "60": 33, "61": 1, "65": 2, "71": 63}, "source": 8, "target": 7}, {"shape_id": {"45": 126, "46": 4, "47": 140, "48": 146}, "direction_id": {}, "headsign": {"B\u00e9tera": 70, "Empalme": 12, "La Canyada": 8, "Ll\u00edria": 76, "Machado": 8, "Mar\u00edtim - Serrer\u00eda": 122, "Paterna": 54, "Seminari - CEU": 66}, "duration_avg": 63.01442307692308, "n_vehicles": 416, "d": 547, "route_I_counts": {"1": 73, "4": 70, "12": 61, "14": 4, "75": 1, "76": 14, "77": 6, "78": 1, "79": 1, "80": 3, "82": 6, "83": 14, "84": 19, "85": 2, "86": 3, "87": 3, "88": 5, "89": 3, "91": 1, "92": 23, "93": 38, "107": 61, "108": 4}, "source": 8, "target": 9}, {"shape_id": {"1": 137, "18": 2, "2": 141, "3": 2, "6": 126}, "direction_id": {}, "headsign": {"L'Alc\u00fadia": 2, "Picassent": 20, "Torrent": 68, "Torrent Avinguda": 140, "Val\u00e8ncia Sud": 134, "Villanueva de Castell\u00f3n": 44}, "duration_avg": 61.568627450980394, "n_vehicles": 408, "d": 547, "route_I_counts": {"2": 70, "5": 68, "13": 63, "15": 2, "40": 7, "41": 6, "43": 20, "44": 1, "45": 12, "46": 1, "47": 4, "48": 14, "49": 2, "50": 3, "52": 1, "58": 22, "59": 13, "60": 33, "61": 1, "65": 2, "71": 63}, "source": 9, "target": 8}, {"shape_id": {"45": 125, "46": 3, "47": 140, "48": 146}, "direction_id": {}, "headsign": {"B\u00e9tera": 70, "Empalme": 12, "La Canyada": 8, "Ll\u00edria": 76, "Machado": 6, "Mar\u00edtim - Serrer\u00eda": 122, "Paterna": 54, "Seminari - CEU": 66}, "duration_avg": 96.27536231884058, "n_vehicles": 414, "d": 708, "route_I_counts": {"1": 73, "4": 70, "12": 61, "14": 3, "75": 1, "76": 14, "77": 6, "78": 1, "79": 1, "80": 3, "82": 6, "83": 14, "84": 19, "85": 2, "86": 3, "87": 3, "88": 5, "89": 3, "91": 1, "92": 23, "93": 38, "107": 61, "108": 3}, "source": 9, "target": 10}, {"shape_id": {"1": 137, "18": 2, "2": 141, "3": 2, "6": 126}, "direction_id": {}, "headsign": {"L'Alc\u00fadia": 2, "Picassent": 20, "Torrent": 68, "Torrent Avinguda": 140, "Val\u00e8ncia Sud": 134, "Villanueva de Castell\u00f3n": 44}, "duration_avg": 99.05147058823529, "n_vehicles": 408, "d": 708, "route_I_counts": {"2": 70, "5": 68, "13": 63, "15": 2, "40": 7, "41": 6, "43": 20, "44": 1, "45": 12, "46": 1, "47": 4, "48": 14, "49": 2, "50": 3, "52": 1, "58": 22, "59": 13, "60": 33, "61": 1, "65": 2, "71": 63}, "source": 10, "target": 9}, {"shape_id": {"45": 125, "46": 3, "47": 140, "48": 146}, "direction_id": {}, "headsign": {"B\u00e9tera": 70, "Empalme": 12, "La Canyada": 8, "Ll\u00edria": 76, "Machado": 6, "Mar\u00edtim - Serrer\u00eda": 122, "Paterna": 54, "Seminari - CEU": 66}, "duration_avg": 107.15217391304348, "n_vehicles": 414, "d": 597, "route_I_counts": {"1": 73, "4": 70, "12": 61, "14": 3, "75": 1, "76": 14, "77": 6, "78": 1, "79": 1, "80": 3, "82": 6, "83": 14, "84": 19, "85": 2, "86": 3, "87": 3, "88": 5, "89": 3, "91": 1, "92": 23, "93": 38, "107": 61, "108": 3}, "source": 10, "target": 11}, {"shape_id": {"1": 137, "18": 2, "2": 141, "3": 2, "6": 126}, "direction_id": {}, "headsign": {"L'Alc\u00fadia": 2, "Picassent": 20, "Torrent": 68, "Torrent Avinguda": 140, "Val\u00e8ncia Sud": 134, "Villanueva de Castell\u00f3n": 44}, "duration_avg": 101.05637254901961, "n_vehicles": 408, "d": 597, "route_I_counts": {"2": 70, "5": 68, "13": 63, "15": 2, "40": 7, "41": 6, "43": 20, "44": 1, "45": 12, "46": 1, "47": 4, "48": 14, "49": 2, "50": 3, "52": 1, "58": 22, "59": 13, "60": 33, "61": 1, "65": 2, "71": 63}, "source": 11, "target": 10}, {"shape_id": {"47": 140, "48": 146}, "direction_id": {}, "headsign": {"B\u00e9tera": 70, "Empalme": 12, "La Canyada": 8, "Ll\u00edria": 76, "Paterna": 54, "Seminari - CEU": 66}, "duration_avg": 114.99300699300699, "n_vehicles": 286, "d": 818, "route_I_counts": {"1": 73, "4": 70, "75": 1, "76": 14, "77": 6, "78": 1, "79": 1, "80": 3, "82": 6, "83": 14, "84": 19, "85": 2, "86": 3, "87": 3, "88": 5, "89": 3, "91": 1, "92": 23, "93": 38}, "source": 11, "target": 12}, {"shape_id": {"45": 125, "46": 3}, "direction_id": {}, "headsign": {"Machado": 6, "Mar\u00edtim - Serrer\u00eda": 122}, "duration_avg": 111.0, "n_vehicles": 128, "d": 690, "route_I_counts": {"12": 61, "14": 3, "107": 61, "108": 3}, "source": 11, "target": 94}, {"shape_id": {"1": 137, "2": 141}, "direction_id": {}, "headsign": {"L'Alc\u00fadia": 2, "Picassent": 20, "Torrent": 68, "Torrent Avinguda": 10, "Val\u00e8ncia Sud": 134, "Villanueva de Castell\u00f3n": 44}, "duration_avg": 114.96402877697842, "n_vehicles": 278, "d": 818, "route_I_counts": {"2": 70, "5": 68, "40": 7, "41": 6, "43": 20, "44": 1, "45": 12, "46": 1, "47": 4, "48": 14, "49": 2, "50": 3, "52": 1, "58": 22, "59": 13, "60": 33, "61": 1}, "source": 12, "target": 11}, {"shape_id": {"47": 140, "48": 146}, "direction_id": {}, "headsign": {"B\u00e9tera": 70, "Empalme": 12, "La Canyada": 8, "Ll\u00edria": 76, "Paterna": 54, "Seminari - CEU": 66}, "duration_avg": 59.44755244755245, "n_vehicles": 286, "d": 542, "route_I_counts": {"1": 73, "4": 70, "75": 1, "76": 14, "77": 6, "78": 1, "79": 1, "80": 3, "82": 6, "83": 14, "84": 19, "85": 2, "86": 3, "87": 3, "88": 5, "89": 3, "91": 1, "92": 23, "93": 38}, "source": 12, "target": 13}, {"shape_id": {"1": 137, "2": 141}, "direction_id": {}, "headsign": {"L'Alc\u00fadia": 2, "Picassent": 20, "Torrent": 68, "Torrent Avinguda": 10, "Val\u00e8ncia Sud": 134, "Villanueva de Castell\u00f3n": 44}, "duration_avg": 61.26618705035971, "n_vehicles": 278, "d": 542, "route_I_counts": {"2": 70, "5": 68, "40": 7, "41": 6, "43": 20, "44": 1, "45": 12, "46": 1, "47": 4, "48": 14, "49": 2, "50": 3, "52": 1, "58": 22, "59": 13, "60": 33, "61": 1}, "source": 13, "target": 12}, {"shape_id": {"47": 140, "48": 146}, "direction_id": {}, "headsign": {"B\u00e9tera": 70, "Empalme": 12, "La Canyada": 8, "Ll\u00edria": 76, "Paterna": 54, "Seminari - CEU": 66}, "duration_avg": 106.02797202797203, "n_vehicles": 286, "d": 1090, "route_I_counts": {"1": 73, "4": 70, "75": 1, "76": 14, "77": 6, "78": 1, "79": 1, "80": 3, "82": 6, "83": 14, "84": 19, "85": 2, "86": 3, "87": 3, "88": 5, "89": 3, "91": 1, "92": 23, "93": 38}, "source": 13, "target": 14}, {"shape_id": {"1": 33, "43": 196, "44": 64, "45": 31, "69": 66}, "direction_id": {}, "headsign": {"Alboraya-Peris Arag\u00f3": 118, "Machado": 16, "Mar\u00edtim - Serrer\u00eda": 128, "Rafelbunyol": 128}, "duration_avg": 103.61794871794872, "n_vehicles": 390, "d": 744, "route_I_counts": {"6": 33, "8": 98, "10": 64, "94": 3, "95": 30, "96": 29, "97": 2, "98": 1, "100": 3, "101": 63, "103": 33, "104": 31}, "source": 13, "target": 73}, {"shape_id": {"3": 194, "6": 66, "7": 67, "70": 70}, "direction_id": {}, "headsign": {"Aeroport": 200, "Av. del Cid": 127, "Riba-roja de T\u00faria": 70}, "duration_avg": 114.639798488665, "n_vehicles": 397, "d": 1102, "route_I_counts": {"7": 35, "9": 97, "11": 67, "63": 2, "64": 3, "66": 3, "67": 32, "68": 1, "69": 28, "70": 63, "72": 33, "73": 33}, "source": 13, "target": 72}, {"shape_id": {"1": 139, "2": 141}, "direction_id": {}, "headsign": {"L'Alc\u00fadia": 2, "Picassent": 20, "Torrent": 68, "Torrent Avinguda": 12, "Val\u00e8ncia Sud": 134, "Villanueva de Castell\u00f3n": 44}, "duration_avg": 107.87142857142857, "n_vehicles": 280, "d": 1090, "route_I_counts": {"2": 70, "5": 69, "40": 7, "41": 6, "43": 20, "44": 1, "45": 12, "46": 1, "47": 4, "48": 14, "49": 2, "50": 3, "52": 1, "58": 22, "59": 14, "60": 33, "61": 1}, "source": 14, "target": 13}, {"shape_id": {"47": 140, "48": 146}, "direction_id": {}, "headsign": {"B\u00e9tera": 70, "Empalme": 12, "La Canyada": 8, "Ll\u00edria": 76, "Paterna": 54, "Seminari - CEU": 66}, "duration_avg": 95.11888111888112, "n_vehicles": 286, "d": 721, "route_I_counts": {"1": 73, "4": 70, "75": 1, "76": 14, "77": 6, "78": 1, "79": 1, "80": 3, "82": 6, "83": 14, "84": 19, "85": 2, "86": 3, "87": 3, "88": 5, "89": 3, "91": 1, "92": 23, "93": 38}, "source": 14, "target": 15}, {"shape_id": {"1": 139, "2": 141}, "direction_id": {}, "headsign": {"L'Alc\u00fadia": 2, "Picassent": 20, "Torrent": 68, "Torrent Avinguda": 12, "Val\u00e8ncia Sud": 134, "Villanueva de Castell\u00f3n": 44}, "duration_avg": 96.21428571428571, "n_vehicles": 280, "d": 721, "route_I_counts": {"2": 70, "5": 69, "40": 7, "41": 6, "43": 20, "44": 1, "45": 12, "46": 1, "47": 4, "48": 14, "49": 2, "50": 3, "52": 1, "58": 22, "59": 14, "60": 33, "61": 1}, "source": 15, "target": 14}, {"shape_id": {"47": 140, "48": 146}, "direction_id": {}, "headsign": {"B\u00e9tera": 70, "Empalme": 12, "La Canyada": 8, "Ll\u00edria": 76, "Paterna": 54, "Seminari - CEU": 66}, "duration_avg": 104.8076923076923, "n_vehicles": 286, "d": 802, "route_I_counts": {"1": 73, "4": 70, "75": 1, "76": 14, "77": 6, "78": 1, "79": 1, "80": 3, "82": 6, "83": 14, "84": 19, "85": 2, "86": 3, "87": 3, "88": 5, "89": 3, "91": 1, "92": 23, "93": 38}, "source": 15, "target": 16}, {"shape_id": {"1": 139, "2": 141}, "direction_id": {}, "headsign": {"L'Alc\u00fadia": 2, "Picassent": 20, "Torrent": 68, "Torrent Avinguda": 12, "Val\u00e8ncia Sud": 134, "Villanueva de Castell\u00f3n": 44}, "duration_avg": 106.15714285714286, "n_vehicles": 280, "d": 802, "route_I_counts": {"2": 70, "5": 69, "40": 7, "41": 6, "43": 20, "44": 1, "45": 12, "46": 1, "47": 4, "48": 14, "49": 2, "50": 3, "52": 1, "58": 22, "59": 14, "60": 33, "61": 1}, "source": 16, "target": 15}, {"shape_id": {"47": 140, "48": 146}, "direction_id": {}, "headsign": {"B\u00e9tera": 70, "Empalme": 12, "La Canyada": 8, "Ll\u00edria": 76, "Paterna": 54, "Seminari - CEU": 66}, "duration_avg": 126.9965034965035, "n_vehicles": 286, "d": 980, "route_I_counts": {"1": 73, "4": 70, "75": 1, "76": 14, "77": 6, "78": 1, "79": 1, "80": 3, "82": 6, "83": 14, "84": 19, "85": 2, "86": 3, "87": 3, "88": 5, "89": 3, "91": 1, "92": 23, "93": 38}, "source": 16, "target": 17}, {"shape_id": {"1": 139, "2": 141}, "direction_id": {}, "headsign": {"L'Alc\u00fadia": 2, "Picassent": 20, "Torrent": 68, "Torrent Avinguda": 12, "Val\u00e8ncia Sud": 134, "Villanueva de Castell\u00f3n": 44}, "duration_avg": 113.01071428571429, "n_vehicles": 280, "d": 980, "route_I_counts": {"2": 70, "5": 69, "40": 7, "41": 6, "43": 20, "44": 1, "45": 12, "46": 1, "47": 4, "48": 14, "49": 2, "50": 3, "52": 1, "58": 22, "59": 14, "60": 33, "61": 1}, "source": 17, "target": 16}, {"shape_id": {"48": 136}, "direction_id": {}, "headsign": {"B\u00e9tera": 70, "Seminari - CEU": 66}, "duration_avg": 110.0, "n_vehicles": 136, "d": 1061, "route_I_counts": {"1": 68, "76": 14, "77": 6, "78": 1, "80": 3, "82": 6, "83": 14, "84": 19, "85": 2, "87": 3}, "source": 17, "target": 18}, {"shape_id": {"47": 138}, "direction_id": {}, "headsign": {"La Canyada": 8, "Ll\u00edria": 76, "Paterna": 54}, "duration_avg": 110.0, "n_vehicles": 138, "d": 910, "route_I_counts": {"4": 69, "88": 5, "89": 3, "92": 23, "93": 38}, "source": 17, "target": 41}, {"shape_id": {"2": 134}, "direction_id": {}, "headsign": {"L'Alc\u00fadia": 2, "Picassent": 20, "Torrent": 68, "Val\u00e8ncia Sud": 6, "Villanueva de Castell\u00f3n": 38}, "duration_avg": 169.1044776119403, "n_vehicles": 134, "d": 1061, "route_I_counts": {"2": 67, "40": 7, "41": 6, "43": 20, "44": 1, "45": 12, "46": 1, "47": 4, "48": 14, "49": 2}, "source": 18, "target": 17}, {"shape_id": {"48": 136}, "direction_id": {}, "headsign": {"B\u00e9tera": 70, "Seminari - CEU": 66}, "duration_avg": 50.44117647058823, "n_vehicles": 136, "d": 726, "route_I_counts": {"1": 68, "76": 14, "77": 6, "78": 1, "80": 3, "82": 6, "83": 14, "84": 19, "85": 2, "87": 3}, "source": 18, "target": 19}, {"shape_id": {"2": 134}, "direction_id": {}, "headsign": {"L'Alc\u00fadia": 2, "Picassent": 20, "Torrent": 68, "Val\u00e8ncia Sud": 6, "Villanueva de Castell\u00f3n": 38}, "duration_avg": 50.8955223880597, "n_vehicles": 134, "d": 726, "route_I_counts": {"2": 67, "40": 7, "41": 6, "43": 20, "44": 1, "45": 12, "46": 1, "47": 4, "48": 14, "49": 2}, "source": 19, "target": 18}, {"shape_id": {"48": 136}, "direction_id": {}, "headsign": {"B\u00e9tera": 70, "Seminari - CEU": 66}, "duration_avg": 108.67647058823529, "n_vehicles": 136, "d": 697, "route_I_counts": {"1": 68, "76": 14, "77": 6, "78": 1, "80": 3, "82": 6, "83": 14, "84": 19, "85": 2, "87": 3}, "source": 19, "target": 20}, {"shape_id": {"2": 134}, "direction_id": {}, "headsign": {"L'Alc\u00fadia": 2, "Picassent": 20, "Torrent": 68, "Val\u00e8ncia Sud": 6, "Villanueva de Castell\u00f3n": 38}, "duration_avg": 109.1044776119403, "n_vehicles": 134, "d": 697, "route_I_counts": {"2": 67, "40": 7, "41": 6, "43": 20, "44": 1, "45": 12, "46": 1, "47": 4, "48": 14, "49": 2}, "source": 20, "target": 19}, {"shape_id": {"48": 136}, "direction_id": {}, "headsign": {"B\u00e9tera": 70, "Seminari - CEU": 66}, "duration_avg": 110.0, "n_vehicles": 136, "d": 1182, "route_I_counts": {"1": 68, "76": 14, "77": 6, "78": 1, "80": 3, "82": 6, "83": 14, "84": 19, "85": 2, "87": 3}, "source": 20, "target": 21}, {"shape_id": {"2": 134}, "direction_id": {}, "headsign": {"L'Alc\u00fadia": 2, "Picassent": 20, "Torrent": 68, "Val\u00e8ncia Sud": 6, "Villanueva de Castell\u00f3n": 38}, "duration_avg": 110.0, "n_vehicles": 134, "d": 1182, "route_I_counts": {"2": 67, "40": 7, "41": 6, "43": 20, "44": 1, "45": 12, "46": 1, "47": 4, "48": 14, "49": 2}, "source": 21, "target": 20}, {"shape_id": {"48": 136}, "direction_id": {}, "headsign": {"B\u00e9tera": 70, "Seminari - CEU": 66}, "duration_avg": 110.0, "n_vehicles": 136, "d": 967, "route_I_counts": {"1": 68, "76": 14, "77": 6, "78": 1, "80": 3, "82": 6, "83": 14, "84": 19, "85": 2, "87": 3}, "source": 21, "target": 22}, {"shape_id": {"2": 134}, "direction_id": {}, "headsign": {"L'Alc\u00fadia": 2, "Picassent": 20, "Torrent": 68, "Val\u00e8ncia Sud": 6, "Villanueva de Castell\u00f3n": 38}, "duration_avg": 110.8955223880597, "n_vehicles": 134, "d": 967, "route_I_counts": {"2": 67, "40": 7, "41": 6, "43": 20, "44": 1, "45": 12, "46": 1, "47": 4, "48": 14, "49": 2}, "source": 22, "target": 21}, {"shape_id": {"48": 136}, "direction_id": {}, "headsign": {"B\u00e9tera": 70, "Seminari - CEU": 66}, "duration_avg": 110.0, "n_vehicles": 136, "d": 1457, "route_I_counts": {"1": 68, "76": 14, "77": 6, "78": 1, "80": 3, "82": 6, "83": 14, "84": 19, "85": 2, "87": 3}, "source": 22, "target": 23}, {"shape_id": {"2": 134}, "direction_id": {}, "headsign": {"L'Alc\u00fadia": 2, "Picassent": 20, "Torrent": 68, "Val\u00e8ncia Sud": 6, "Villanueva de Castell\u00f3n": 38}, "duration_avg": 110.0, "n_vehicles": 134, "d": 1457, "route_I_counts": {"2": 67, "40": 7, "41": 6, "43": 20, "44": 1, "45": 12, "46": 1, "47": 4, "48": 14, "49": 2}, "source": 23, "target": 22}, {"shape_id": {"48": 136}, "direction_id": {}, "headsign": {"B\u00e9tera": 70, "Seminari - CEU": 66}, "duration_avg": 55.88235294117647, "n_vehicles": 136, "d": 727, "route_I_counts": {"1": 68, "76": 14, "77": 6, "78": 1, "80": 3, "82": 6, "83": 14, "84": 19, "85": 2, "87": 3}, "source": 23, "target": 24}, {"shape_id": {"2": 134}, "direction_id": {}, "headsign": {"L'Alc\u00fadia": 2, "Picassent": 20, "Torrent": 68, "Val\u00e8ncia Sud": 6, "Villanueva de Castell\u00f3n": 38}, "duration_avg": 50.0, "n_vehicles": 134, "d": 727, "route_I_counts": {"2": 67, "40": 7, "41": 6, "43": 20, "44": 1, "45": 12, "46": 1, "47": 4, "48": 14, "49": 2}, "source": 24, "target": 23}, {"shape_id": {"48": 70}, "direction_id": {}, "headsign": {"B\u00e9tera": 70}, "duration_avg": 174.28571428571428, "n_vehicles": 70, "d": 2283, "route_I_counts": {"1": 35, "77": 6, "78": 1, "82": 6, "84": 19, "87": 3}, "source": 24, "target": 25}, {"shape_id": {"2": 68}, "direction_id": {}, "headsign": {"Picassent": 12, "Torrent": 40, "Val\u00e8ncia Sud": 2, "Villanueva de Castell\u00f3n": 14}, "duration_avg": 178.8235294117647, "n_vehicles": 68, "d": 2283, "route_I_counts": {"2": 34, "40": 7, "41": 6, "43": 20, "44": 1}, "source": 25, "target": 24}, {"shape_id": {"48": 70}, "direction_id": {}, "headsign": {"B\u00e9tera": 70}, "duration_avg": 290.0, "n_vehicles": 70, "d": 3663, "route_I_counts": {"1": 35, "84": 35}, "source": 25, "target": 26}, {"shape_id": {"14": 1, "2": 69}, "direction_id": {}, "headsign": {"Masies": 35, "Picassent": 6, "Torrent": 20, "Torrent Avinguda": 1, "Val\u00e8ncia Sud": 1, "Villanueva de Castell\u00f3n": 7}, "duration_avg": 412.0, "n_vehicles": 70, "d": 3663, "route_I_counts": {"2": 34, "3": 1, "43": 35}, "source": 26, "target": 25}, {"shape_id": {"48": 70}, "direction_id": {}, "headsign": {"B\u00e9tera": 70}, "duration_avg": 238.85714285714286, "n_vehicles": 70, "d": 1567, "route_I_counts": {"1": 35, "84": 35}, "source": 26, "target": 27}, {"shape_id": {"14": 1, "2": 69}, "direction_id": {}, "headsign": {"Masies": 35, "Picassent": 6, "Torrent": 20, "Torrent Avinguda": 1, "Val\u00e8ncia Sud": 1, "Villanueva de Castell\u00f3n": 7}, "duration_avg": 260.0, "n_vehicles": 70, "d": 1567, "route_I_counts": {"2": 34, "3": 1, "43": 35}, "source": 27, "target": 26}, {"shape_id": {"48": 44}, "direction_id": {}, "headsign": {"B\u00e9tera": 12, "Empalme": 4, "Seminari - CEU": 28}, "duration_avg": 290.0, "n_vehicles": 44, "d": 3735, "route_I_counts": {"1": 22, "75": 2, "76": 14, "77": 6}, "source": 28, "target": 29}, {"shape_id": {"2": 44}, "direction_id": {}, "headsign": {"Villanueva de Castell\u00f3n": 44}, "duration_avg": 300.0, "n_vehicles": 44, "d": 3735, "route_I_counts": {"2": 22, "40": 7, "45": 12, "50": 3}, "source": 29, "target": 28}, {"shape_id": {"48": 44}, "direction_id": {}, "headsign": {"B\u00e9tera": 12, "Empalme": 4, "Seminari - CEU": 28}, "duration_avg": 230.0, "n_vehicles": 44, "d": 3006, "route_I_counts": {"1": 22, "75": 2, "76": 14, "77": 6}, "source": 29, "target": 30}, {"shape_id": {"2": 44}, "direction_id": {}, "headsign": {"Villanueva de Castell\u00f3n": 44}, "duration_avg": 227.27272727272728, "n_vehicles": 44, "d": 3006, "route_I_counts": {"2": 22, "40": 7, "45": 12, "50": 3}, "source": 30, "target": 29}, {"shape_id": {"48": 44}, "direction_id": {}, "headsign": {"B\u00e9tera": 12, "Empalme": 4, "Seminari - CEU": 28}, "duration_avg": 170.0, "n_vehicles": 44, "d": 3347, "route_I_counts": {"1": 22, "75": 2, "76": 14, "77": 6}, "source": 30, "target": 31}, {"shape_id": {"2": 44}, "direction_id": {}, "headsign": {"Villanueva de Castell\u00f3n": 44}, "duration_avg": 170.0, "n_vehicles": 44, "d": 3347, "route_I_counts": {"2": 22, "40": 7, "45": 12, "50": 3}, "source": 31, "target": 30}, {"shape_id": {"48": 44}, "direction_id": {}, "headsign": {"B\u00e9tera": 12, "Empalme": 4, "Seminari - CEU": 28}, "duration_avg": 170.0, "n_vehicles": 44, "d": 2280, "route_I_counts": {"1": 22, "75": 2, "76": 14, "77": 6}, "source": 31, "target": 32}, {"shape_id": {"2": 44}, "direction_id": {}, "headsign": {"Villanueva de Castell\u00f3n": 44}, "duration_avg": 115.45454545454545, "n_vehicles": 44, "d": 2280, "route_I_counts": {"2": 22, "40": 7, "45": 12, "50": 3}, "source": 32, "target": 31}, {"shape_id": {"48": 46}, "direction_id": {}, "headsign": {"B\u00e9tera": 14, "Empalme": 4, "Seminari - CEU": 28}, "duration_avg": 110.0, "n_vehicles": 46, "d": 2629, "route_I_counts": {"1": 23, "75": 2, "76": 14, "77": 6, "78": 1}, "source": 32, "target": 33}, {"shape_id": {"2": 48}, "direction_id": {}, "headsign": {"L'Alc\u00fadia": 4, "Villanueva de Castell\u00f3n": 44}, "duration_avg": 182.08333333333334, "n_vehicles": 48, "d": 2629, "route_I_counts": {"2": 24, "40": 7, "45": 12, "46": 1, "50": 3, "54": 1}, "source": 33, "target": 32}, {"shape_id": {"48": 46}, "direction_id": {}, "headsign": {"B\u00e9tera": 14, "Empalme": 4, "Seminari - CEU": 28}, "duration_avg": 209.1304347826087, "n_vehicles": 46, "d": 1256, "route_I_counts": {"1": 23, "75": 2, "76": 14, "77": 6, "78": 1}, "source": 33, "target": 34}, {"shape_id": {"2": 48}, "direction_id": {}, "headsign": {"L'Alc\u00fadia": 4, "Villanueva de Castell\u00f3n": 44}, "duration_avg": 117.5, "n_vehicles": 48, "d": 1256, "route_I_counts": {"2": 24, "40": 7, "45": 12, "46": 1, "50": 3, "54": 1}, "source": 34, "target": 33}, {"shape_id": {"48": 46}, "direction_id": {}, "headsign": {"B\u00e9tera": 14, "Empalme": 4, "Seminari - CEU": 28}, "duration_avg": 230.0, "n_vehicles": 46, "d": 3807, "route_I_counts": {"1": 23, "75": 2, "76": 14, "77": 6, "78": 1}, "source": 34, "target": 35}, {"shape_id": {"2": 48}, "direction_id": {}, "headsign": {"L'Alc\u00fadia": 4, "Villanueva de Castell\u00f3n": 44}, "duration_avg": 279.1666666666667, "n_vehicles": 48, "d": 3807, "route_I_counts": {"2": 24, "40": 7, "45": 12, "46": 1, "50": 3, "54": 1}, "source": 35, "target": 34}, {"shape_id": {"48": 46}, "direction_id": {}, "headsign": {"B\u00e9tera": 14, "Empalme": 4, "Seminari - CEU": 28}, "duration_avg": 170.0, "n_vehicles": 46, "d": 2095, "route_I_counts": {"1": 23, "75": 2, "76": 14, "77": 6, "78": 1}, "source": 35, "target": 36}, {"shape_id": {"2": 48}, "direction_id": {}, "headsign": {"L'Alc\u00fadia": 4, "Villanueva de Castell\u00f3n": 44}, "duration_avg": 165.0, "n_vehicles": 48, "d": 2095, "route_I_counts": {"2": 24, "40": 7, "45": 12, "46": 1, "50": 3, "54": 1}, "source": 36, "target": 35}, {"shape_id": {"48": 46}, "direction_id": {}, "headsign": {"B\u00e9tera": 14, "Empalme": 4, "Seminari - CEU": 28}, "duration_avg": 231.30434782608697, "n_vehicles": 46, "d": 3089, "route_I_counts": {"1": 23, "75": 2, "76": 14, "77": 6, "78": 1}, "source": 36, "target": 37}, {"shape_id": {"2": 48}, "direction_id": {}, "headsign": {"L'Alc\u00fadia": 4, "Villanueva de Castell\u00f3n": 44}, "duration_avg": 230.0, "n_vehicles": 48, "d": 3089, "route_I_counts": {"2": 24, "40": 7, "45": 12, "46": 1, "50": 3, "54": 1}, "source": 37, "target": 36}, {"shape_id": {"48": 46}, "direction_id": {}, "headsign": {"B\u00e9tera": 14, "Empalme": 4, "Seminari - CEU": 28}, "duration_avg": 170.0, "n_vehicles": 46, "d": 3622, "route_I_counts": {"1": 23, "75": 2, "76": 14, "77": 6, "78": 1}, "source": 37, "target": 38}, {"shape_id": {"2": 48}, "direction_id": {}, "headsign": {"L'Alc\u00fadia": 4, "Villanueva de Castell\u00f3n": 44}, "duration_avg": 215.0, "n_vehicles": 48, "d": 3622, "route_I_counts": {"2": 24, "40": 7, "45": 12, "46": 1, "50": 3, "54": 1}, "source": 38, "target": 37}, {"shape_id": {"48": 46}, "direction_id": {}, "headsign": {"B\u00e9tera": 14, "Empalme": 4, "Seminari - CEU": 28}, "duration_avg": 172.6086956521739, "n_vehicles": 46, "d": 3541, "route_I_counts": {"1": 23, "75": 2, "76": 14, "77": 6, "78": 1}, "source": 38, "target": 39}, {"shape_id": {"2": 48}, "direction_id": {}, "headsign": {"L'Alc\u00fadia": 4, "Villanueva de Castell\u00f3n": 44}, "duration_avg": 172.5, "n_vehicles": 48, "d": 3541, "route_I_counts": {"2": 24, "40": 7, "45": 12, "46": 1, "50": 3, "54": 1}, "source": 39, "target": 38}, {"shape_id": {"48": 44}, "direction_id": {}, "headsign": {"B\u00e9tera": 14, "Empalme": 2, "Seminari - CEU": 28}, "duration_avg": 271.8181818181818, "n_vehicles": 44, "d": 1328, "route_I_counts": {"1": 22, "75": 1, "76": 14, "77": 6, "78": 1}, "source": 39, "target": 0}, {"shape_id": {"45": 126, "46": 4, "47": 14}, "direction_id": {}, "headsign": {"Empalme": 2, "La Canyada": 2, "Ll\u00edria": 8, "Machado": 8, "Mar\u00edtim - Serrer\u00eda": 122, "Val\u00e8ncia Sud": 2}, "duration_avg": 230.0, "n_vehicles": 144, "d": 1066, "route_I_counts": {"4": 7, "12": 61, "14": 4, "90": 1, "91": 1, "93": 5, "107": 61, "108": 4}, "source": 40, "target": 4}, {"shape_id": {"47": 138}, "direction_id": {}, "headsign": {"La Canyada": 8, "Ll\u00edria": 76, "Paterna": 54}, "duration_avg": 110.0, "n_vehicles": 138, "d": 632, "route_I_counts": {"4": 69, "88": 5, "89": 3, "92": 23, "93": 38}, "source": 41, "target": 42}, {"shape_id": {"1": 138}, "direction_id": {}, "headsign": {"Torrent Avinguda": 12, "Val\u00e8ncia Sud": 126}, "duration_avg": 110.14492753623189, "n_vehicles": 138, "d": 910, "route_I_counts": {"5": 68, "58": 22, "59": 14, "60": 33, "61": 1}, "source": 41, "target": 17}, {"shape_id": {"47": 138}, "direction_id": {}, "headsign": {"La Canyada": 8, "Ll\u00edria": 76, "Paterna": 54}, "duration_avg": 50.0, "n_vehicles": 138, "d": 623, "route_I_counts": {"4": 69, "88": 5, "89": 3, "92": 23, "93": 38}, "source": 42, "target": 43}, {"shape_id": {"1": 138}, "direction_id": {}, "headsign": {"Torrent Avinguda": 12, "Val\u00e8ncia Sud": 126}, "duration_avg": 110.14492753623189, "n_vehicles": 138, "d": 632, "route_I_counts": {"5": 68, "58": 22, "59": 14, "60": 33, "61": 1}, "source": 42, "target": 41}, {"shape_id": {"47": 138}, "direction_id": {}, "headsign": {"La Canyada": 8, "Ll\u00edria": 76, "Paterna": 54}, "duration_avg": 170.0, "n_vehicles": 138, "d": 909, "route_I_counts": {"4": 69, "88": 5, "89": 3, "92": 23, "93": 38}, "source": 43, "target": 44}, {"shape_id": {"1": 138}, "direction_id": {}, "headsign": {"Torrent Avinguda": 12, "Val\u00e8ncia Sud": 126}, "duration_avg": 50.14492753623188, "n_vehicles": 138, "d": 623, "route_I_counts": {"5": 68, "58": 22, "59": 14, "60": 33, "61": 1}, "source": 43, "target": 42}, {"shape_id": {"47": 138}, "direction_id": {}, "headsign": {"La Canyada": 8, "Ll\u00edria": 76, "Paterna": 54}, "duration_avg": 73.47826086956522, "n_vehicles": 138, "d": 659, "route_I_counts": {"4": 69, "88": 5, "89": 3, "92": 23, "93": 38}, "source": 44, "target": 45}, {"shape_id": {"1": 138}, "direction_id": {}, "headsign": {"Torrent Avinguda": 12, "Val\u00e8ncia Sud": 126}, "duration_avg": 170.14492753623188, "n_vehicles": 138, "d": 909, "route_I_counts": {"5": 68, "58": 22, "59": 14, "60": 33, "61": 1}, "source": 44, "target": 43}, {"shape_id": {"47": 84}, "direction_id": {}, "headsign": {"La Canyada": 8, "Ll\u00edria": 76}, "duration_avg": 110.23809523809524, "n_vehicles": 84, "d": 1361, "route_I_counts": {"4": 41, "88": 2, "89": 3, "93": 38}, "source": 45, "target": 46}, {"shape_id": {"1": 138}, "direction_id": {}, "headsign": {"Torrent Avinguda": 12, "Val\u00e8ncia Sud": 126}, "duration_avg": 50.14492753623188, "n_vehicles": 138, "d": 659, "route_I_counts": {"5": 68, "58": 22, "59": 14, "60": 33, "61": 1}, "source": 45, "target": 44}, {"shape_id": {"47": 84}, "direction_id": {}, "headsign": {"La Canyada": 8, "Ll\u00edria": 76}, "duration_avg": 110.23809523809524, "n_vehicles": 84, "d": 1015, "route_I_counts": {"4": 41, "88": 2, "89": 3, "93": 38}, "source": 46, "target": 47}, {"shape_id": {"1": 80}, "direction_id": {}, "headsign": {"Torrent Avinguda": 10, "Val\u00e8ncia Sud": 70}, "duration_avg": 150.75, "n_vehicles": 80, "d": 1361, "route_I_counts": {"5": 39, "58": 22, "59": 14, "60": 5}, "source": 46, "target": 45}, {"shape_id": {"47": 84}, "direction_id": {}, "headsign": {"La Canyada": 8, "Ll\u00edria": 76}, "duration_avg": 201.1904761904762, "n_vehicles": 84, "d": 2607, "route_I_counts": {"4": 41, "88": 2, "89": 3, "93": 38}, "source": 47, "target": 48}, {"shape_id": {"1": 80}, "direction_id": {}, "headsign": {"Torrent Avinguda": 10, "Val\u00e8ncia Sud": 70}, "duration_avg": 110.25, "n_vehicles": 80, "d": 1015, "route_I_counts": {"5": 39, "58": 22, "59": 14, "60": 5}, "source": 47, "target": 46}, {"shape_id": {"47": 76}, "direction_id": {}, "headsign": {"Ll\u00edria": 76}, "duration_avg": 170.0, "n_vehicles": 76, "d": 1542, "route_I_counts": {"4": 38, "89": 2, "93": 36}, "source": 48, "target": 49}, {"shape_id": {"1": 80}, "direction_id": {}, "headsign": {"Torrent Avinguda": 10, "Val\u00e8ncia Sud": 70}, "duration_avg": 170.25, "n_vehicles": 80, "d": 2607, "route_I_counts": {"5": 39, "58": 22, "59": 14, "60": 5}, "source": 48, "target": 47}, {"shape_id": {"47": 76}, "direction_id": {}, "headsign": {"Ll\u00edria": 76}, "duration_avg": 110.0, "n_vehicles": 76, "d": 1501, "route_I_counts": {"4": 38, "89": 2, "93": 36}, "source": 49, "target": 50}, {"shape_id": {"1": 72}, "direction_id": {}, "headsign": {"Torrent Avinguda": 10, "Val\u00e8ncia Sud": 62}, "duration_avg": 210.0, "n_vehicles": 72, "d": 1542, "route_I_counts": {"5": 36, "58": 22, "59": 14}, "source": 49, "target": 48}, {"shape_id": {"47": 76}, "direction_id": {}, "headsign": {"Ll\u00edria": 76}, "duration_avg": 170.0, "n_vehicles": 76, "d": 1406, "route_I_counts": {"4": 38, "89": 2, "93": 36}, "source": 50, "target": 51}, {"shape_id": {"1": 72}, "direction_id": {}, "headsign": {"Torrent Avinguda": 10, "Val\u00e8ncia Sud": 62}, "duration_avg": 110.0, "n_vehicles": 72, "d": 1501, "route_I_counts": {"5": 36, "58": 22, "59": 14}, "source": 50, "target": 49}, {"shape_id": {"47": 76}, "direction_id": {}, "headsign": {"Ll\u00edria": 76}, "duration_avg": 50.0, "n_vehicles": 76, "d": 710, "route_I_counts": {"4": 38, "89": 2, "93": 36}, "source": 51, "target": 52}, {"shape_id": {"1": 74}, "direction_id": {}, "headsign": {"Torrent Avinguda": 10, "Val\u00e8ncia Sud": 64}, "duration_avg": 170.0, "n_vehicles": 74, "d": 1406, "route_I_counts": {"5": 37, "58": 23, "59": 14}, "source": 51, "target": 50}, {"shape_id": {"47": 76}, "direction_id": {}, "headsign": {"Ll\u00edria": 76}, "duration_avg": 50.0, "n_vehicles": 76, "d": 785, "route_I_counts": {"4": 38, "89": 2, "93": 36}, "source": 52, "target": 53}, {"shape_id": {"1": 74}, "direction_id": {}, "headsign": {"Torrent Avinguda": 10, "Val\u00e8ncia Sud": 64}, "duration_avg": 50.0, "n_vehicles": 74, "d": 710, "route_I_counts": {"5": 37, "58": 23, "59": 14}, "source": 52, "target": 51}, {"shape_id": {"47": 76}, "direction_id": {}, "headsign": {"Ll\u00edria": 76}, "duration_avg": 50.0, "n_vehicles": 76, "d": 918, "route_I_counts": {"4": 38, "89": 2, "93": 36}, "source": 53, "target": 54}, {"shape_id": {"1": 74}, "direction_id": {}, "headsign": {"Torrent Avinguda": 10, "Val\u00e8ncia Sud": 64}, "duration_avg": 50.0, "n_vehicles": 74, "d": 785, "route_I_counts": {"5": 37, "58": 23, "59": 14}, "source": 53, "target": 52}, {"shape_id": {"47": 74}, "direction_id": {}, "headsign": {"Ll\u00edria": 74}, "duration_avg": 201.8918918918919, "n_vehicles": 74, "d": 2348, "route_I_counts": {"4": 37, "89": 2, "93": 35}, "source": 54, "target": 55}, {"shape_id": {"1": 74}, "direction_id": {}, "headsign": {"Torrent Avinguda": 10, "Val\u00e8ncia Sud": 64}, "duration_avg": 50.0, "n_vehicles": 74, "d": 918, "route_I_counts": {"5": 37, "58": 23, "59": 14}, "source": 54, "target": 53}, {"shape_id": {"47": 74}, "direction_id": {}, "headsign": {"Ll\u00edria": 74}, "duration_avg": 170.0, "n_vehicles": 74, "d": 1751, "route_I_counts": {"4": 37, "89": 2, "93": 35}, "source": 55, "target": 56}, {"shape_id": {"1": 74}, "direction_id": {}, "headsign": {"Torrent Avinguda": 10, "Val\u00e8ncia Sud": 64}, "duration_avg": 170.0, "n_vehicles": 74, "d": 2348, "route_I_counts": {"5": 37, "58": 23, "59": 14}, "source": 55, "target": 54}, {"shape_id": {"47": 74}, "direction_id": {}, "headsign": {"Ll\u00edria": 74}, "duration_avg": 172.43243243243242, "n_vehicles": 74, "d": 849, "route_I_counts": {"4": 37, "93": 37}, "source": 56, "target": 57}, {"shape_id": {"1": 74}, "direction_id": {}, "headsign": {"Torrent Avinguda": 10, "Val\u00e8ncia Sud": 64}, "duration_avg": 228.3783783783784, "n_vehicles": 74, "d": 1751, "route_I_counts": {"5": 37, "58": 23, "59": 14}, "source": 56, "target": 55}, {"shape_id": {"47": 74}, "direction_id": {}, "headsign": {"Ll\u00edria": 74}, "duration_avg": 360.0, "n_vehicles": 74, "d": 2722, "route_I_counts": {"4": 37, "93": 37}, "source": 57, "target": 58}, {"shape_id": {"1": 74}, "direction_id": {}, "headsign": {"Benaguasil 1r": 37, "Torrent Avinguda": 5, "Val\u00e8ncia Sud": 32}, "duration_avg": 200.0, "n_vehicles": 74, "d": 849, "route_I_counts": {"5": 37, "59": 37}, "source": 57, "target": 56}, {"shape_id": {"1": 74}, "direction_id": {}, "headsign": {"Benaguasil 1r": 37, "Torrent Avinguda": 5, "Val\u00e8ncia Sud": 32}, "duration_avg": 472.43243243243245, "n_vehicles": 74, "d": 2722, "route_I_counts": {"5": 37, "59": 37}, "source": 58, "target": 57}, {"shape_id": {"69": 68}, "direction_id": {}, "headsign": {"Alboraya-Peris Arag\u00f3": 60, "Machado": 8}, "duration_avg": 110.0, "n_vehicles": 68, "d": 1244, "route_I_counts": {"6": 34, "94": 4, "95": 30}, "source": 59, "target": 60}, {"shape_id": {"69": 68}, "direction_id": {}, "headsign": {"Alboraya-Peris Arag\u00f3": 60, "Machado": 8}, "duration_avg": 115.0, "n_vehicles": 68, "d": 1361, "route_I_counts": {"6": 34, "94": 4, "95": 30}, "source": 60, "target": 61}, {"shape_id": {"70": 70}, "direction_id": {}, "headsign": {"Riba-roja de T\u00faria": 70}, "duration_avg": 120.0, "n_vehicles": 70, "d": 1244, "route_I_counts": {"7": 35, "66": 3, "67": 32}, "source": 60, "target": 59}, {"shape_id": {"69": 68}, "direction_id": {}, "headsign": {"Alboraya-Peris Arag\u00f3": 60, "Machado": 8}, "duration_avg": 115.0, "n_vehicles": 68, "d": 2160, "route_I_counts": {"6": 34, "94": 4, "95": 30}, "source": 61, "target": 62}, {"shape_id": {"70": 70}, "direction_id": {}, "headsign": {"Riba-roja de T\u00faria": 70}, "duration_avg": 115.0, "n_vehicles": 70, "d": 1361, "route_I_counts": {"7": 35, "66": 3, "67": 32}, "source": 61, "target": 60}, {"shape_id": {"69": 68}, "direction_id": {}, "headsign": {"Alboraya-Peris Arag\u00f3": 60, "Machado": 8}, "duration_avg": 270.0, "n_vehicles": 68, "d": 3381, "route_I_counts": {"6": 34, "94": 4, "95": 30}, "source": 62, "target": 63}, {"shape_id": {"70": 70}, "direction_id": {}, "headsign": {"Riba-roja de T\u00faria": 70}, "duration_avg": 115.0, "n_vehicles": 70, "d": 2160, "route_I_counts": {"7": 35, "66": 3, "67": 32}, "source": 62, "target": 61}, {"shape_id": {"69": 68}, "direction_id": {}, "headsign": {"Alboraya-Peris Arag\u00f3": 60, "Machado": 8}, "duration_avg": 170.0, "n_vehicles": 68, "d": 1633, "route_I_counts": {"6": 34, "94": 4, "95": 30}, "source": 63, "target": 64}, {"shape_id": {"70": 70}, "direction_id": {}, "headsign": {"Riba-roja de T\u00faria": 70}, "duration_avg": 230.0, "n_vehicles": 70, "d": 3381, "route_I_counts": {"7": 35, "66": 3, "67": 32}, "source": 63, "target": 62}, {"shape_id": {"1": 33, "43": 132, "44": 33, "69": 68}, "direction_id": {}, "headsign": {"Alboraya-Peris Arag\u00f3": 60, "Machado": 14, "Mar\u00edtim - Serrer\u00eda": 66, "Rafelbunyol": 126}, "duration_avg": 97.0, "n_vehicles": 266, "d": 780, "route_I_counts": {"6": 34, "8": 66, "10": 33, "94": 4, "95": 30, "100": 3, "101": 63, "103": 33}, "source": 64, "target": 65}, {"shape_id": {"3": 134, "6": 33, "7": 33}, "direction_id": {}, "headsign": {"Aeroport": 200}, "duration_avg": 125.0, "n_vehicles": 200, "d": 660, "route_I_counts": {"9": 67, "11": 33, "64": 3, "68": 1, "70": 63, "72": 33}, "source": 64, "target": 81}, {"shape_id": {"70": 70}, "direction_id": {}, "headsign": {"Riba-roja de T\u00faria": 70}, "duration_avg": 210.0, "n_vehicles": 70, "d": 1633, "route_I_counts": {"7": 35, "66": 3, "67": 32}, "source": 64, "target": 63}, {"shape_id": {"1": 33, "43": 132, "44": 33, "69": 68}, "direction_id": {}, "headsign": {"Alboraya-Peris Arag\u00f3": 60, "Machado": 14, "Mar\u00edtim - Serrer\u00eda": 66, "Rafelbunyol": 126}, "duration_avg": 114.5, "n_vehicles": 266, "d": 901, "route_I_counts": {"6": 34, "8": 66, "10": 33, "94": 4, "95": 30, "100": 3, "101": 63, "103": 33}, "source": 65, "target": 66}, {"shape_id": {"3": 134, "6": 33, "7": 33, "70": 70}, "direction_id": {}, "headsign": {"Aeroport": 200, "Riba-roja de T\u00faria": 70}, "duration_avg": 96.5, "n_vehicles": 270, "d": 780, "route_I_counts": {"7": 35, "9": 67, "11": 33, "64": 3, "66": 3, "67": 32, "68": 1, "70": 63, "72": 33}, "source": 65, "target": 64}, {"shape_id": {"1": 33, "43": 132, "44": 33, "69": 68}, "direction_id": {}, "headsign": {"Alboraya-Peris Arag\u00f3": 60, "Machado": 14, "Mar\u00edtim - Serrer\u00eda": 66, "Rafelbunyol": 126}, "duration_avg": 107.5, "n_vehicles": 266, "d": 855, "route_I_counts": {"6": 34, "8": 66, "10": 33, "94": 4, "95": 30, "100": 3, "101": 63, "103": 33}, "source": 66, "target": 67}, {"shape_id": {"3": 134, "6": 33, "7": 33, "70": 70}, "direction_id": {}, "headsign": {"Aeroport": 200, "Riba-roja de T\u00faria": 70}, "duration_avg": 106.0, "n_vehicles": 270, "d": 901, "route_I_counts": {"7": 35, "9": 67, "11": 33, "64": 3, "66": 3, "67": 32, "68": 1, "70": 63, "72": 33}, "source": 66, "target": 65}, {"shape_id": {"1": 33, "43": 132, "44": 33, "69": 68}, "direction_id": {}, "headsign": {"Alboraya-Peris Arag\u00f3": 60, "Machado": 14, "Mar\u00edtim - Serrer\u00eda": 66, "Rafelbunyol": 126}, "duration_avg": 105.0, "n_vehicles": 266, "d": 841, "route_I_counts": {"6": 34, "8": 66, "10": 33, "94": 4, "95": 30, "100": 3, "101": 63, "103": 33}, "source": 67, "target": 68}, {"shape_id": {"3": 134, "6": 33, "7": 33, "70": 70}, "direction_id": {}, "headsign": {"Aeroport": 200, "Riba-roja de T\u00faria": 70}, "duration_avg": 107.5, "n_vehicles": 270, "d": 855, "route_I_counts": {"7": 35, "9": 67, "11": 33, "64": 3, "66": 3, "67": 32, "68": 1, "70": 63, "72": 33}, "source": 67, "target": 66}, {"shape_id": {"1": 33, "43": 132, "44": 33, "69": 66}, "direction_id": {}, "headsign": {"Alboraya-Peris Arag\u00f3": 60, "Machado": 12, "Mar\u00edtim - Serrer\u00eda": 66, "Rafelbunyol": 126}, "duration_avg": 105.5, "n_vehicles": 264, "d": 778, "route_I_counts": {"6": 33, "8": 66, "10": 33, "94": 3, "95": 30, "100": 3, "101": 63, "103": 33}, "source": 68, "target": 69}, {"shape_id": {"3": 134, "6": 33, "7": 33, "70": 70}, "direction_id": {}, "headsign": {"Aeroport": 200, "Riba-roja de T\u00faria": 70}, "duration_avg": 103.5, "n_vehicles": 270, "d": 841, "route_I_counts": {"7": 35, "9": 67, "11": 33, "64": 3, "66": 3, "67": 32, "68": 1, "70": 63, "72": 33}, "source": 68, "target": 67}, {"shape_id": {"1": 33, "43": 132, "44": 33, "69": 66}, "direction_id": {}, "headsign": {"Alboraya-Peris Arag\u00f3": 60, "Machado": 12, "Mar\u00edtim - Serrer\u00eda": 66, "Rafelbunyol": 126}, "duration_avg": 61.5, "n_vehicles": 264, "d": 575, "route_I_counts": {"6": 33, "8": 66, "10": 33, "94": 3, "95": 30, "100": 3, "101": 63, "103": 33}, "source": 69, "target": 70}, {"shape_id": {"3": 134, "6": 33, "7": 33, "70": 70}, "direction_id": {}, "headsign": {"Aeroport": 200, "Riba-roja de T\u00faria": 70}, "duration_avg": 106.0, "n_vehicles": 270, "d": 778, "route_I_counts": {"7": 35, "9": 67, "11": 33, "64": 3, "66": 3, "67": 32, "68": 1, "70": 63, "72": 33}, "source": 69, "target": 68}, {"shape_id": {"1": 33, "43": 132, "44": 33, "69": 66}, "direction_id": {}, "headsign": {"Alboraya-Peris Arag\u00f3": 60, "Machado": 12, "Mar\u00edtim - Serrer\u00eda": 66, "Rafelbunyol": 126}, "duration_avg": 104.25, "n_vehicles": 264, "d": 982, "route_I_counts": {"6": 33, "8": 66, "10": 33, "94": 3, "95": 30, "100": 3, "101": 63, "103": 33}, "source": 70, "target": 71}, {"shape_id": {"3": 134, "6": 33, "7": 33, "70": 70}, "direction_id": {}, "headsign": {"Aeroport": 200, "Riba-roja de T\u00faria": 70}, "duration_avg": 63.0, "n_vehicles": 270, "d": 575, "route_I_counts": {"7": 35, "9": 67, "11": 33, "64": 3, "66": 3, "67": 32, "68": 1, "70": 63, "72": 33}, "source": 70, "target": 69}, {"shape_id": {"1": 33, "43": 132, "44": 33, "69": 66}, "direction_id": {}, "headsign": {"Alboraya-Peris Arag\u00f3": 60, "Machado": 12, "Mar\u00edtim - Serrer\u00eda": 66, "Rafelbunyol": 126}, "duration_avg": 103.125, "n_vehicles": 264, "d": 905, "route_I_counts": {"6": 33, "8": 66, "10": 33, "94": 3, "95": 30, "100": 3, "101": 63, "103": 33}, "source": 71, "target": 72}, {"shape_id": {"3": 134, "6": 33, "7": 33, "70": 70}, "direction_id": {}, "headsign": {"Aeroport": 200, "Riba-roja de T\u00faria": 70}, "duration_avg": 101.61111111111111, "n_vehicles": 270, "d": 982, "route_I_counts": {"7": 35, "9": 67, "11": 33, "64": 3, "66": 3, "67": 32, "68": 1, "70": 63, "72": 33}, "source": 71, "target": 70}, {"shape_id": {"1": 33, "43": 196, "44": 64, "45": 31, "69": 66}, "direction_id": {}, "headsign": {"Alboraya-Peris Arag\u00f3": 118, "Machado": 16, "Mar\u00edtim - Serrer\u00eda": 128, "Rafelbunyol": 128}, "duration_avg": 108.0, "n_vehicles": 390, "d": 1102, "route_I_counts": {"6": 33, "8": 98, "10": 64, "94": 3, "95": 30, "96": 29, "97": 2, "98": 1, "100": 3, "101": 63, "103": 33, "104": 31}, "source": 72, "target": 13}, {"shape_id": {"3": 134, "6": 33, "7": 33, "70": 70}, "direction_id": {}, "headsign": {"Aeroport": 200, "Riba-roja de T\u00faria": 70}, "duration_avg": 108.9888888888889, "n_vehicles": 270, "d": 905, "route_I_counts": {"7": 35, "9": 67, "11": 33, "64": 3, "66": 3, "67": 32, "68": 1, "70": 63, "72": 33}, "source": 72, "target": 71}, {"shape_id": {"1": 33, "43": 196, "44": 64, "45": 31, "69": 66}, "direction_id": {}, "headsign": {"Alboraya-Peris Arag\u00f3": 118, "Machado": 16, "Mar\u00edtim - Serrer\u00eda": 128, "Rafelbunyol": 128}, "duration_avg": 98.12564102564103, "n_vehicles": 390, "d": 644, "route_I_counts": {"6": 33, "8": 98, "10": 64, "94": 3, "95": 30, "96": 29, "97": 2, "98": 1, "100": 3, "101": 63, "103": 33, "104": 31}, "source": 73, "target": 74}, {"shape_id": {"3": 194, "6": 67, "7": 67, "70": 70}, "direction_id": {}, "headsign": {"Aeroport": 200, "Av. del Cid": 128, "Riba-roja de T\u00faria": 70}, "duration_avg": 101.5, "n_vehicles": 398, "d": 744, "route_I_counts": {"7": 35, "9": 97, "11": 67, "63": 2, "64": 3, "66": 3, "67": 32, "68": 1, "69": 28, "70": 63, "72": 33, "73": 34}, "source": 73, "target": 13}, {"shape_id": {"18": 2, "3": 2, "6": 126}, "direction_id": {}, "headsign": {"Torrent Avinguda": 130}, "duration_avg": 155.5, "n_vehicles": 130, "d": 1002, "route_I_counts": {"13": 63, "15": 2, "65": 2, "71": 63}, "source": 74, "target": 94}, {"shape_id": {"1": 32, "43": 196, "44": 63, "45": 156, "46": 3, "69": 66}, "direction_id": {}, "headsign": {"Alboraya-Peris Arag\u00f3": 118, "Machado": 22, "Mar\u00edtim - Serrer\u00eda": 248, "Rafelbunyol": 128}, "duration_avg": 83.75, "n_vehicles": 516, "d": 587, "route_I_counts": {"6": 33, "8": 98, "10": 63, "12": 61, "14": 3, "94": 3, "95": 30, "96": 29, "97": 2, "98": 1, "100": 3, "101": 63, "103": 32, "104": 31, "107": 61, "108": 3}, "source": 74, "target": 75}, {"shape_id": {"3": 194, "6": 67, "7": 67, "70": 70}, "direction_id": {}, "headsign": {"Aeroport": 200, "Av. del Cid": 128, "Riba-roja de T\u00faria": 70}, "duration_avg": 97.51507537688443, "n_vehicles": 398, "d": 644, "route_I_counts": {"7": 35, "9": 97, "11": 67, "63": 2, "64": 3, "66": 3, "67": 32, "68": 1, "69": 28, "70": 63, "72": 33, "73": 34}, "source": 74, "target": 73}, {"shape_id": {"18": 2, "3": 198, "6": 193, "7": 67, "70": 70}, "direction_id": {}, "headsign": {"Aeroport": 202, "Av. del Cid": 128, "Riba-roja de T\u00faria": 70, "Torrent Avinguda": 130}, "duration_avg": 64.0056603773585, "n_vehicles": 530, "d": 587, "route_I_counts": {"7": 35, "9": 98, "11": 67, "13": 63, "15": 2, "63": 2, "64": 3, "65": 2, "66": 3, "67": 32, "68": 1, "69": 28, "70": 64, "71": 63, "72": 33, "73": 34}, "source": 75, "target": 74}, {"shape_id": {"1": 32, "44": 67, "45": 163}, "direction_id": {}, "headsign": {"Mar\u00edtim - Serrer\u00eda": 262}, "duration_avg": 109.5, "n_vehicles": 262, "d": 621, "route_I_counts": {"10": 67, "12": 64, "103": 32, "104": 31, "105": 7, "107": 61}, "source": 75, "target": 90}, {"shape_id": {"43": 196, "45": 4, "46": 4, "69": 66}, "direction_id": {}, "headsign": {"Alboraya-Peris Arag\u00f3": 118, "Machado": 24, "Rafelbunyol": 128}, "duration_avg": 98.83333333333333, "n_vehicles": 270, "d": 614, "route_I_counts": {"6": 33, "8": 98, "14": 4, "94": 3, "95": 30, "96": 29, "97": 2, "98": 1, "100": 3, "101": 63, "106": 1, "108": 3}, "source": 75, "target": 76}, {"shape_id": {"18": 5, "3": 209, "70": 70}, "direction_id": {}, "headsign": {"Aeroport": 136, "Alameda": 14, "Av. del Cid": 60, "Riba-roja de T\u00faria": 70, "Torrent Avinguda": 4}, "duration_avg": 111.5, "n_vehicles": 284, "d": 614, "route_I_counts": {"7": 35, "9": 102, "15": 5, "62": 7, "63": 2, "64": 3, "65": 2, "66": 3, "67": 32, "68": 1, "69": 28, "70": 64}, "source": 76, "target": 75}, {"shape_id": {"43": 194, "45": 4, "46": 4, "69": 66}, "direction_id": {}, "headsign": {"Alboraya-Peris Arag\u00f3": 118, "Machado": 24, "Rafelbunyol": 126}, "duration_avg": 112.0, "n_vehicles": 268, "d": 763, "route_I_counts": {"6": 33, "8": 97, "14": 4, "94": 3, "95": 30, "96": 29, "97": 2, "98": 1, "100": 3, "101": 62, "106": 1, "108": 3}, "source": 76, "target": 77}, {"shape_id": {"18": 5, "3": 209, "70": 70}, "direction_id": {}, "headsign": {"Aeroport": 136, "Alameda": 14, "Av. del Cid": 60, "Riba-roja de T\u00faria": 70, "Torrent Avinguda": 4}, "duration_avg": 111.5, "n_vehicles": 284, "d": 763, "route_I_counts": {"7": 35, "9": 102, "15": 5, "62": 7, "63": 2, "64": 3, "65": 2, "66": 3, "67": 32, "68": 1, "69": 28, "70": 64}, "source": 77, "target": 76}, {"shape_id": {"43": 194, "45": 4, "46": 4, "69": 66}, "direction_id": {}, "headsign": {"Alboraya-Peris Arag\u00f3": 118, "Machado": 24, "Rafelbunyol": 126}, "duration_avg": 103.0, "n_vehicles": 268, "d": 896, "route_I_counts": {"6": 33, "8": 97, "14": 4, "94": 3, "95": 30, "96": 29, "97": 2, "98": 1, "100": 3, "101": 62, "106": 1, "108": 3}, "source": 77, "target": 78}, {"shape_id": {"18": 5, "3": 209, "70": 70}, "direction_id": {}, "headsign": {"Aeroport": 136, "Alameda": 14, "Av. del Cid": 60, "Riba-roja de T\u00faria": 70, "Torrent Avinguda": 4}, "duration_avg": 103.5, "n_vehicles": 284, "d": 896, "route_I_counts": {"7": 35, "9": 102, "15": 5, "62": 7, "63": 2, "64": 3, "65": 2, "66": 3, "67": 32, "68": 1, "69": 28, "70": 64}, "source": 78, "target": 77}, {"shape_id": {"43": 190, "69": 60}, "direction_id": {}, "headsign": {"Alboraya-Peris Arag\u00f3": 118, "Rafelbunyol": 132}, "duration_avg": 102.5, "n_vehicles": 250, "d": 472, "route_I_counts": {"6": 30, "8": 95, "95": 30, "96": 29, "98": 1, "101": 62, "102": 3}, "source": 78, "target": 79}, {"shape_id": {"43": 190, "69": 60}, "direction_id": {}, "headsign": {"Alboraya-Peris Arag\u00f3": 118, "Rafelbunyol": 132}, "duration_avg": 119.36, "n_vehicles": 250, "d": 619, "route_I_counts": {"6": 30, "8": 95, "95": 30, "96": 29, "98": 1, "101": 62, "102": 3}, "source": 79, "target": 80}, {"shape_id": {"3": 186, "70": 64}, "direction_id": {}, "headsign": {"Aeroport": 130, "Av. del Cid": 56, "Riba-roja de T\u00faria": 64}, "duration_avg": 102.0, "n_vehicles": 250, "d": 472, "route_I_counts": {"7": 32, "9": 93, "67": 32, "68": 1, "69": 28, "70": 64}, "source": 79, "target": 78}, {"shape_id": {"3": 186, "70": 64}, "direction_id": {}, "headsign": {"Aeroport": 130, "Av. del Cid": 56, "Riba-roja de T\u00faria": 64}, "duration_avg": 109.0, "n_vehicles": 250, "d": 619, "route_I_counts": {"7": 32, "9": 93, "67": 32, "68": 1, "69": 28, "70": 64}, "source": 80, "target": 79}, {"shape_id": {"43": 132}, "direction_id": {}, "headsign": {"Rafelbunyol": 132}, "duration_avg": 170.0, "n_vehicles": 132, "d": 1290, "route_I_counts": {"8": 66, "98": 1, "101": 62, "102": 3}, "source": 80, "target": 82}, {"shape_id": {"1": 33, "43": 134, "44": 33}, "direction_id": {}, "headsign": {"Machado": 8, "Mar\u00edtim - Serrer\u00eda": 66, "Rafelbunyol": 126}, "duration_avg": 121.345, "n_vehicles": 200, "d": 660, "route_I_counts": {"8": 67, "10": 33, "100": 4, "101": 63, "103": 33}, "source": 81, "target": 64}, {"shape_id": {"3": 128}, "direction_id": {}, "headsign": {"Aeroport": 128}, "duration_avg": 237.8125, "n_vehicles": 128, "d": 1290, "route_I_counts": {"9": 64, "70": 64}, "source": 82, "target": 80}, {"shape_id": {"43": 132}, "direction_id": {}, "headsign": {"Rafelbunyol": 132}, "duration_avg": 210.0, "n_vehicles": 132, "d": 1768, "route_I_counts": {"8": 66, "98": 1, "101": 62, "102": 3}, "source": 82, "target": 83}, {"shape_id": {"3": 128}, "direction_id": {}, "headsign": {"Aeroport": 128}, "duration_avg": 170.0, "n_vehicles": 128, "d": 1768, "route_I_counts": {"9": 64, "70": 64}, "source": 83, "target": 82}, {"shape_id": {"43": 132}, "direction_id": {}, "headsign": {"Rafelbunyol": 132}, "duration_avg": 170.0, "n_vehicles": 132, "d": 1038, "route_I_counts": {"8": 66, "98": 1, "101": 62, "102": 3}, "source": 83, "target": 84}, {"shape_id": {"3": 128}, "direction_id": {}, "headsign": {"Aeroport": 128}, "duration_avg": 150.0, "n_vehicles": 128, "d": 1038, "route_I_counts": {"9": 64, "70": 64}, "source": 84, "target": 83}, {"shape_id": {"43": 132}, "direction_id": {}, "headsign": {"Rafelbunyol": 132}, "duration_avg": 110.0, "n_vehicles": 132, "d": 1015, "route_I_counts": {"8": 66, "98": 1, "101": 62, "102": 3}, "source": 84, "target": 85}, {"shape_id": {"3": 128}, "direction_id": {}, "headsign": {"Aeroport": 128}, "duration_avg": 110.0, "n_vehicles": 128, "d": 1015, "route_I_counts": {"9": 64, "70": 64}, "source": 85, "target": 84}, {"shape_id": {"43": 132}, "direction_id": {}, "headsign": {"Museros": 66, "Rafelbunyol": 66}, "duration_avg": 329.6969696969697, "n_vehicles": 132, "d": 1924, "route_I_counts": {"8": 66, "101": 66}, "source": 85, "target": 86}, {"shape_id": {"43": 65}, "direction_id": {}, "headsign": {"Rafelbunyol": 65}, "duration_avg": 900.0, "n_vehicles": 65, "d": 5037, "route_I_counts": {"101": 65}, "source": 85, "target": 89}, {"shape_id": {"43": 65}, "direction_id": {}, "headsign": {"La Pobla de Farnals": 65}, "duration_avg": 660.0, "n_vehicles": 65, "d": 4098, "route_I_counts": {"101": 65}, "source": 85, "target": 88}, {"shape_id": {"43": 65}, "direction_id": {}, "headsign": {"Massamagrell": 65}, "duration_avg": 540.0, "n_vehicles": 65, "d": 3105, "route_I_counts": {"101": 65}, "source": 85, "target": 87}, {"shape_id": {"3": 128}, "direction_id": {}, "headsign": {"Aeroport": 64, "Albalat dels Sorells": 64}, "duration_avg": 290.9375, "n_vehicles": 128, "d": 1924, "route_I_counts": {"9": 64, "70": 64}, "source": 86, "target": 85}, {"shape_id": {"43": 66}, "direction_id": {}, "headsign": {"Rafelbunyol": 66}, "duration_avg": 100.0, "n_vehicles": 66, "d": 1204, "route_I_counts": {"8": 66}, "source": 86, "target": 87}, {"shape_id": {"3": 64}, "direction_id": {}, "headsign": {"Aeroport": 64}, "duration_avg": 119.375, "n_vehicles": 64, "d": 1204, "route_I_counts": {"9": 64}, "source": 87, "target": 86}, {"shape_id": {"43": 66}, "direction_id": {}, "headsign": {"Rafelbunyol": 66}, "duration_avg": 100.0, "n_vehicles": 66, "d": 1010, "route_I_counts": {"8": 66}, "source": 87, "target": 88}, {"shape_id": {"3": 64}, "direction_id": {}, "headsign": {"Albalat dels Sorells": 64}, "duration_avg": 540.0, "n_vehicles": 64, "d": 3105, "route_I_counts": {"70": 64}, "source": 87, "target": 85}, {"shape_id": {"3": 64}, "direction_id": {}, "headsign": {"Aeroport": 64}, "duration_avg": 100.0, "n_vehicles": 64, "d": 1010, "route_I_counts": {"9": 64}, "source": 88, "target": 87}, {"shape_id": {"43": 66}, "direction_id": {}, "headsign": {"Rafelbunyol": 66}, "duration_avg": 60.0, "n_vehicles": 66, "d": 1015, "route_I_counts": {"8": 66}, "source": 88, "target": 89}, {"shape_id": {"3": 64}, "direction_id": {}, "headsign": {"Albalat dels Sorells": 64}, "duration_avg": 660.0, "n_vehicles": 64, "d": 4098, "route_I_counts": {"70": 64}, "source": 88, "target": 85}, {"shape_id": {"3": 64}, "direction_id": {}, "headsign": {"Aeroport": 64}, "duration_avg": 40.0, "n_vehicles": 64, "d": 1015, "route_I_counts": {"9": 64}, "source": 89, "target": 88}, {"shape_id": {"3": 64}, "direction_id": {}, "headsign": {"Albalat dels Sorells": 64}, "duration_avg": 900.0, "n_vehicles": 64, "d": 5037, "route_I_counts": {"70": 64}, "source": 89, "target": 85}, {"shape_id": {"1": 32, "44": 67, "45": 163}, "direction_id": {}, "headsign": {"Mar\u00edtim - Serrer\u00eda": 262}, "duration_avg": 101.0, "n_vehicles": 262, "d": 710, "route_I_counts": {"10": 67, "12": 64, "103": 32, "104": 31, "105": 7, "107": 61}, "source": 90, "target": 91}, {"shape_id": {"6": 195, "7": 67}, "direction_id": {}, "headsign": {"Aeroport": 66, "Alameda": 2, "Av. del Cid": 68, "Torrent Avinguda": 126}, "duration_avg": 107.0, "n_vehicles": 262, "d": 621, "route_I_counts": {"11": 67, "13": 64, "71": 63, "72": 33, "73": 34, "74": 1}, "source": 90, "target": 75}, {"shape_id": {"1": 32, "44": 67, "45": 163}, "direction_id": {}, "headsign": {"Mar\u00edtim - Serrer\u00eda": 262}, "duration_avg": 109.02290076335878, "n_vehicles": 262, "d": 772, "route_I_counts": {"10": 67, "12": 64, "103": 32, "104": 31, "105": 7, "107": 61}, "source": 91, "target": 92}, {"shape_id": {"6": 195, "7": 67}, "direction_id": {}, "headsign": {"Aeroport": 66, "Alameda": 2, "Av. del Cid": 68, "Torrent Avinguda": 126}, "duration_avg": 100.5, "n_vehicles": 262, "d": 710, "route_I_counts": {"11": 67, "13": 64, "71": 63, "72": 33, "73": 34, "74": 1}, "source": 91, "target": 90}, {"shape_id": {"1": 32, "44": 67, "45": 163}, "direction_id": {}, "headsign": {"Mar\u00edtim - Serrer\u00eda": 262}, "duration_avg": 91.13740458015268, "n_vehicles": 262, "d": 439, "route_I_counts": {"10": 67, "12": 64, "103": 32, "104": 31, "105": 7, "107": 61}, "source": 92, "target": 93}, {"shape_id": {"6": 195, "7": 67}, "direction_id": {}, "headsign": {"Aeroport": 66, "Alameda": 2, "Av. del Cid": 68, "Torrent Avinguda": 126}, "duration_avg": 109.5, "n_vehicles": 262, "d": 772, "route_I_counts": {"11": 67, "13": 64, "71": 63, "72": 33, "73": 34, "74": 1}, "source": 92, "target": 91}, {"shape_id": {"6": 195, "7": 67}, "direction_id": {}, "headsign": {"Aeroport": 66, "Alameda": 2, "Av. del Cid": 68, "Torrent Avinguda": 126}, "duration_avg": 104.0, "n_vehicles": 262, "d": 439, "route_I_counts": {"11": 67, "13": 64, "71": 63, "72": 33, "73": 34, "74": 1}, "source": 93, "target": 92}, {"shape_id": {"18": 2, "3": 2, "6": 126}, "direction_id": {}, "headsign": {"Torrent Avinguda": 130}, "duration_avg": 111.5, "n_vehicles": 130, "d": 690, "route_I_counts": {"13": 63, "15": 2, "65": 2, "71": 63}, "source": 94, "target": 11}, {"shape_id": {"45": 125, "46": 3}, "direction_id": {}, "headsign": {"Machado": 6, "Mar\u00edtim - Serrer\u00eda": 122}, "duration_avg": 165.0, "n_vehicles": 128, "d": 1002, "route_I_counts": {"12": 61, "14": 3, "107": 61, "108": 3}, "source": 94, "target": 74}]}